flutter_channel/__init__.py
flutter_channel/host.py
flutter_channel/message.py
flutter_channel/methodCall.py
flutter_channel/reply.py
flutter_channel/test.py
flutter_channel/test2.py
flutter_channel/channels/__channel.py
flutter_channel/channels/__init__.py
flutter_channel/channels/__jsonchannel.py
flutter_channel/channels/__methodChannel.py
flutter_channel/channels/__stringchannel.py
flutter_channel/exceptions/__init__.py
flutter_channel/exceptions/__methodChannel.py
flutter_channel/utils/__init__.py
flutter_channel/utils/boradcast.py
flutter_channel-0.0.4.dist-info/LICENSE
flutter_channel-0.0.4.dist-info/METADATA
flutter_channel-0.0.4.dist-info/WHEEL
flutter_channel-0.0.4.dist-info/top_level.txt
flutter_channel-0.0.4.dist-info/RECORD
