Metadata-Version: 2.1
Name: flutter-channel
Version: 0.0.4
Summary: implement for Platform Channels for python
Home-page: https://github.com/Ghali01/flutter_channel
Author: ghale abduallah
Author-email: galeab121@gmail.con
Classifier: Programming Language :: Python :: 3
Classifier: License :: OSI Approved :: MIT License
Classifier: Operating System :: Microsoft :: Windows
Requires-Python: >=3.7
License-File: LICENSE
